SPARQLBurger/SPARQLQueryBuilder.py
SPARQLBurger/SPARQLSyntaxTerms.py
SPARQLBurger/__init__.py
tests/__init__.py
tests/test_SPARQLQueryBuilder.py
SPARQL_Burger-1.0.2.dist-info/LICENSE.txt
SPARQL_Burger-1.0.2.dist-info/METADATA
SPARQL_Burger-1.0.2.dist-info/WHEEL
SPARQL_Burger-1.0.2.dist-info/top_level.txt
SPARQL_Burger-1.0.2.dist-info/RECORD
