Metadata-Version: 2.1
Name: SPARQL-Burger
Version: 1.0.2
Summary: A Python SPARQL query builder that automates the generation of SPARQL graph patterns, SPARQL Select and SPARQL Update queries.
Home-page: https://github.com/panmitz/SPARQL-Burger
Author: Panos Mitzias
Author-email: pmitzias@gmail.com
License: UNKNOWN
Platform: UNKNOWN
Classifier: Programming Language :: Python
Classifier: Programming Language :: Python :: 2
Classifier: Programming Language :: Python :: 3
Classifier: Operating System :: OS Independent
